tests/__init__.py
tests/test_virtual_bundle.py
virtual_modi/__init__.py
virtual_modi/virtual_bundle.py
virtual_modi/util/__init__.py
virtual_modi/util/connection_util.py
virtual_modi/util/message_util.py
virtual_modi/util/topology_util.py
virtual_modi/virtual_module/__init__.py
virtual_modi/virtual_module/virtual_module.py
virtual_modi/virtual_module/virtual_input_module/__init__.py
virtual_modi/virtual_module/virtual_input_module/virtual_button.py
virtual_modi/virtual_module/virtual_input_module/virtual_dial.py
virtual_modi/virtual_module/virtual_input_module/virtual_env.py
virtual_modi/virtual_module/virtual_input_module/virtual_gyro.py
virtual_modi/virtual_module/virtual_input_module/virtual_ir.py
virtual_modi/virtual_module/virtual_input_module/virtual_mic.py
virtual_modi/virtual_module/virtual_input_module/virtual_ultrasonic.py
virtual_modi/virtual_module/virtual_output_module/__init__.py
virtual_modi/virtual_module/virtual_output_module/virtual_display.py
virtual_modi/virtual_module/virtual_output_module/virtual_led.py
virtual_modi/virtual_module/virtual_output_module/virtual_motor.py
virtual_modi/virtual_module/virtual_output_module/virtual_speaker.py
virtual_modi/virtual_module/virtual_setup_module/__init__.py
virtual_modi/virtual_module/virtual_setup_module/virtual_network.py
virtual_modi-0.3.1.dist-info/LICENSE
virtual_modi-0.3.1.dist-info/METADATA
virtual_modi-0.3.1.dist-info/WHEEL
virtual_modi-0.3.1.dist-info/top_level.txt
virtual_modi-0.3.1.dist-info/RECORD
