Metadata-Version: 2.1
Name: virtual-modi
Version: 0.3.1
Summary: Implementation of virtual MODI modules written in Python.
Home-page: https://github.com/LUXROBO/virtual-modi
Author: LUXROBO
Author-email: tech@luxrobo.com
License: MIT
Platform: UNKNOWN
Classifier: Programming Language :: Python :: 3.6
Classifier: Programming Language :: Python :: 3.7
Classifier: Programming Language :: Python :: 3.8
Classifier: License :: OSI Approved :: MIT License
Classifier: Operating System :: OS Independent
